hdl_tlm_if/__build_num__.py
hdl_tlm_if/__init__.py
hdl_tlm_if/__main__.py
hdl_tlm_if/decorators.py
hdl_tlm_if/pkginfo.py
hdl_tlm_if/tlm_ifc.py
hdl_tlm_if/tlm_ifc_rgy.py
hdl_tlm_if/tlm_method.py
pyhdl_tlm_if-0.0.1.dist-info/LICENSE
pyhdl_tlm_if-0.0.1.dist-info/METADATA
pyhdl_tlm_if-0.0.1.dist-info/WHEEL
pyhdl_tlm_if-0.0.1.dist-info/entry_points.txt
pyhdl_tlm_if-0.0.1.dist-info/top_level.txt
pyhdl_tlm_if-0.0.1.dist-info/RECORD
