Metadata-Version: 2.1
Name: pyhdl-tlm-if
Version: 0.0.1
Summary: Python interface for HDL programming interfaces
Home-page: https://github.com/fvutils/pyhdl-if
Author: Matthew Ballance
Author-email: matt.ballance@gmail.com
License: Apache 2.0
Keywords: SystemVerilog,Verilog,VHDL,RTL,Python
License-File: LICENSE
Requires-Dist: pyhdl-call-if
